raleigh/__init__.py
raleigh/algebra/__init__.py
raleigh/algebra/cublas_handle.py
raleigh/algebra/cublas_wrap.py
raleigh/algebra/cuda_wrap.py
raleigh/algebra/dense_cblas.py
raleigh/algebra/dense_cpu.py
raleigh/algebra/dense_cublas.py
raleigh/algebra/dense_matrix.py
raleigh/algebra/dense_ndarray.py
raleigh/algebra/dense_numpy.py
raleigh/algebra/env.py
raleigh/algebra/mkl_wrap.py
raleigh/algebra/sparse_mkl.py
raleigh/algebra/verbosity.py
raleigh/core/__init__.py
raleigh/core/solver.py
raleigh/examples/__init__.py
raleigh/examples/buckling_evp.py
raleigh/examples/core_solver.py
raleigh/examples/laplace.py
raleigh/examples/sparse_evp.py
raleigh/examples/truncated_svd.py
raleigh/examples/eigenimages/__init__.py
raleigh/examples/eigenimages/compute_eigenimages.py
raleigh/examples/eigenimages/convert_lfw.py
raleigh/examples/eigenimages/icompute_eigenimages.py
raleigh/examples/eigenimages/show_errors.py
raleigh/examples/pca/__init__.py
raleigh/examples/pca/generate_matrix.py
raleigh/examples/pca/incremental_pca.py
raleigh/examples/pca/interactive_pca.py
raleigh/examples/pca/pca_simple.py
raleigh/examples/pca/pca_smart.py
raleigh/examples/pca/pca_update.py
raleigh/interfaces/__init__.py
raleigh/interfaces/lra.py
raleigh/interfaces/partial_hevp.py
raleigh/interfaces/partial_svd.py
raleigh/interfaces/pca.py
raleigh/interfaces/truncated_svd.py
raleigh-1.3.5.dist-info/LICENSE
raleigh-1.3.5.dist-info/METADATA
raleigh-1.3.5.dist-info/WHEEL
raleigh-1.3.5.dist-info/top_level.txt
raleigh-1.3.5.dist-info/RECORD
