Metadata-Version: 2.1
Name: raleigh
Version: 1.3.5
Summary: RAL eigensolver for real symmetric and Hermitian problems
Home-page: https://github.com/evgueni-ovtchinnikov/raleigh
Author: Evgueni Ovtchinnikov
Author-email: evgueni.ovtchinnikov@stfc.ac.uk
License: BSD-3-Clause
Classifier: Development Status :: 5 - Production/Stable
Classifier: Intended Audience :: Developers
Classifier: Intended Audience :: Science/Research
Classifier: License :: OSI Approved :: BSD License
Classifier: Natural Language :: English
Classifier: Operating System :: OS Independent
Classifier: Programming Language :: Python
Classifier: Programming Language :: Python :: 2.7
Classifier: Programming Language :: Python :: 3
Classifier: Topic :: Scientific/Engineering
Classifier: Topic :: Software Development :: Libraries :: Python Modules
License-File: LICENSE
